topicgpt_python/__init__.py
topicgpt_python/assignment.py
topicgpt_python/correction.py
topicgpt_python/data_sample.py
topicgpt_python/generation_1.py
topicgpt_python/generation_2.py
topicgpt_python/metrics.py
topicgpt_python/refinement.py
topicgpt_python/utils.py
topicgpt_python-0.2.7.dist-info/METADATA
topicgpt_python-0.2.7.dist-info/WHEEL
topicgpt_python-0.2.7.dist-info/top_level.txt
topicgpt_python-0.2.7.dist-info/RECORD
