Metadata-Version: 2.1
Name: topicgpt_python
Version: 0.2.7
Summary: Official implementation of TopicGPT: A Prompt-based Topic Modeling Framework (NAACL'24)
Home-page: https://chtmp223.github.io/topicGPT
Author: Chau Minh Pham
Author-email: chautm.pham@gmail.com
Classifier: Programming Language :: Python :: 3
Classifier: Operating System :: OS Independent
Requires-Python: >=3.9
Requires-Dist: anytree<3.0.0,>=2.12.1
Requires-Dist: numpy<2.0.0,>=1.26.2
Requires-Dist: openai<2.0.0,>=1.54.3
Requires-Dist: pandas<3.0.0,>=2.1.3
Requires-Dist: pytz<2025.0,>=2024.2
Requires-Dist: regex<2025.0,>=2024.11.6
Requires-Dist: requests<3.0.0,>=2.32.3
Requires-Dist: sentence-transformers<4.0.0,>=3.2.1
Requires-Dist: tenacity<10.0.0,>=9.0.0
Requires-Dist: tiktoken<0.8.0,>=0.7.0
Requires-Dist: tqdm<5.0.0,>=4.67.0
Requires-Dist: vllm<1.0.0,>=0.6.3.post1
Requires-Dist: vertexai<2.0.0,>=1.71.1
Requires-Dist: anthropic<1.0.0,>=0.39.0
Requires-Dist: pyyaml
Requires-Dist: google
Requires-Dist: google-generativeai
